display_tty/__init__.py
display_tty/__main__.py
display_tty/src/__init__.py
display_tty/src/aliases.py
display_tty/src/colours.py
display_tty/src/constants.py
display_tty/src/initialiser.py
display_tty/src/instances.py
display_tty/src/log_level_tracker.py
display_tty/src/my_disp.py
display_tty-1.1.16.dist-info/licenses/LICENSE
display_tty-1.1.16.dist-info/METADATA
display_tty-1.1.16.dist-info/WHEEL
display_tty-1.1.16.dist-info/top_level.txt
display_tty-1.1.16.dist-info/RECORD
