Metadata-Version: 2.4
Name: display_tty
Version: 1.1.16
Summary: A module that allows you to display text with a few boilers (i.e. put your text in a square for titles). It also allows to log to the terminal by wrapping around the logging library.
Home-page: https://github.com/Hanra-s-work/display_tty
Author: Henry Letellier
Author-email: Henry Letellier <henrysoftwarehouse@protonmail.com>
Maintainer-email: Henry Letellier <henrysoftwarehouse@protonmail.com>
License-Expression: MIT
Project-URL: Homepage, https://github.com/Hanra-s-work/display_tty
Project-URL: Documentation, https://github.com/Hanra-s-work/display_tty/blob/main/README.md
Project-URL: Repository, https://github.com/Hanra-s-work/display_tty.git
Project-URL: Issues, https://github.com/Hanra-s-work/display_tty/issues
Keywords: logger,terminal,logging,lightweight,colour,stdout,stderr,optimised,wrapper,pure python,python
Classifier: Environment :: Console
Classifier: Natural Language :: English
Classifier: Development Status :: 5 - Production/Stable
Classifier: Operating System :: OS Independent
Classifier: Programming Language :: Python :: 3
Classifier: Programming Language :: Python :: 3.9
Classifier: Programming Language :: Python :: 3.10
Classifier: Programming Language :: Python :: 3.11
Classifier: Programming Language :: Python :: 3.12
Classifier: Programming Language :: Python :: 3.13
Classifier: Programming Language :: Python :: 3.14
Classifier: Programming Language :: Python :: 3.15
Requires-Python: >=3.9
License-File: LICENSE
Requires-Dist: colorlog==6.10.1
Dynamic: author
Dynamic: home-page
Dynamic: license-file
